[{"text":"thankful for so much on this wonderful holiday. happy thanksgiving","label":0},{"text":"strong mind, soft heart. healthy body, happy soul. one of the photos from my recent shoot with","label":0},{"text":"littlebeachhousemalibu la little beach house malibu","label":0},{"text":"love this woman and all she stands for. friend of one and friend of mine. friendlyhouse","label":0},{"text":"golden gate bridge lookout","label":0},{"text":"coldplay! thank you user rosebowl vip suites","label":0},{"text":"oh my! i forgot to post about run yesterday week , day ! marinecorpsmarathon","label":2},{"text":"yass the full like up for hsmf is out","label":1},{"text":"user was my favorite part of hard. goodvibes hardsummer summer hard summer","label":1},{"text":"thanks for playing my song beautiful beverly hills, california","label":0},{"text":"last trip of ! can t wait to see my lover los angeles international airport user","label":0},{"text":"salading blue barn gourmet in san francisco, ca w user","label":1},{"text":"layered caramel cold brew. heaven on ice. jump start espresso","label":0},{"text":"jerry getting down in the aisle at user until a stranger catches him lol michaels","label":2},{"text":"forever exploring huntingtonbeach california downtown mainstreet huntington beach,","label":0},{"text":"includednotfree photo from spaceneedle w user","label":2},{"text":"i love my people chelle nhayes chardx silent steven san pedro square market bar","label":1},{"text":"insert inspirational quote here sf foreveryoung bay bridge sf","label":0},{"text":"my favourite place in california yosemitenationalpark california yosemite wilderness","label":1},{"text":"user that blows. i would have bought just to resell to an idiot who would buy them","label":2},{"text":"wolfpack missingfab tapiaresidence dec friendly","label":0},{"text":"fashion show mall user in las vegas, nv w user","label":1},{"text":"dang...even i wanna hold her hand las vegas strip","label":1},{"text":"ciao bello !!!! so nice to see you today user theivy the ivy","label":1},{"text":"i really like this one death valley national park","label":2},{"text":"just fell in luv tbh","label":2},{"text":"a big sale for a happy monday get a head start on those stocking stuffers and december baby","label":1},{"text":"rose bowl with my godmama rose bowl stadium","label":0},{"text":"the reward for making it through monday myunicornlife silver lake, los angeles","label":1},{"text":"kind of in love with her livcofactory livbeyond user livcyclingusa keystone canyon","label":0},{"text":"out new menus!! thanks cassiet you are so talented we are so lucky to have you","label":0},{"text":"elvis is in the building! christmas visitor pup cuddles west hollywood, california","label":0},{"text":"pabebe user the westin monache resort, mammoth","label":2},{"text":"just as wrong as they can be. port hueneme, california","label":2},{"text":"vegas by default las vegas strip","label":1},{"text":"happy i found my lil cuz this year, and even happier he s as crazy as me the jungle","label":0},{"text":"these fun size stocking stuffers are the perfect gift for the globe trotters, road warriors,","label":1},{"text":"mater and i in cars land. that s mater... like tamater with out the ta ...","label":2},{"text":"you can start again in any new way right now. beachwood drive","label":0},{"text":"my lovely place harrypotter hogwarts universalstudios la ca usa the wizarding world","label":1},{"text":"anyone else put a full face of make up on at am when they can t sleep?? just me?? alrighty then...","label":2},{"text":"i found the original! wot u sayin tho it was you yeah??? san jose, california","label":2},{"text":"someone messin with me","label":2},{"text":"eat my shorts bart simpson universal studios hollywood","label":2},{"text":"rambo loves his new porch and people watching every morning carlsbad, california","label":1},{"text":"rise and shine sleepy head catsofinstagram seattle seattle meowtropolitan","label":1},{"text":"hi my name is luna and i am the newest member of the starrantino family iminlove with","label":0},{"text":"the best people get me the best presents newbagalert pacific heights, san francisco","label":1},{"text":"user no way","label":2},{"text":"left my in santa cruz pacifichwy santa cruz light house","label":0},{"text":"acabo de conocer a mickey disney california adventure user in anaheim, ca w user","label":1},{"text":"well, he only comes once a year! reno, nevada","label":2},{"text":"i m crying laughing smh stopvegans savethegrass toofunny user","label":2},{"text":"with fresno s finest!!! planetasiamedallions amp user strummer s","label":0},{"text":"piece of heaven california beverly hills, california","label":0},{"text":"everybody need to rest, even superman superman west hollywood, california","label":2},{"text":"my heart warmfuzzies thetimehascome photo credit user the gastro grill","label":0},{"text":"user frfr years of ineptitude is tuff to turn around","label":2},{"text":"eiffel in love with you. eiffel tower, las vegas","label":1},{"text":"radar love . the dog is called radar. he s my therapy dog this weekend. dog lazysunday","label":0},{"text":"she amuses herself with her own reflection elsanewby babylife strollerchristmaslights","label":2},{"text":"snap chat frontp universal studios hollywood","label":2},{"text":"amazing dinner bonapettit il fornaio beverly hills","label":0},{"text":"slow mo !!!! lasvegastopgolf happygilmore is my hero top golf","label":2},{"text":"happy birthday jazmine!!! birthdaygirl richs sdpix rich s san diego","label":0},{"text":"hi beautiful niece san dimas canyon park","label":0},{"text":"holdthedoor got hodor dolby theatre","label":0},{"text":"lol these two are so funny! riley just looks scared, not sure why","label":2},{"text":"thank you ryanschude for this wonderful creation! repost ryanschude sometimes the gods","label":0},{"text":"back in stock on love u baby onesies oakland, california","label":0},{"text":"days of love fun tacos tequila music beach pool bae baecationmissioncomplete","label":1},{"text":"that moment you take a zero on your final","label":2},{"text":"blonde is my favorite color braidsandbalayage kalynsieminskihair modernsalon americansalon","label":1},{"text":"such a great album adele cents store","label":0},{"text":"homecoming beauty! proudmama daughter loveher serrano country","label":1},{"text":"good to know what went wrong. redfoxx echo park lake","label":2},{"text":"lead with love had an epic time being part of the peace rally in losangeles with k or","label":0},{"text":"this guy chocolate hazelnut semifreddo sixthcoursesf sfmission onlyinsf chocolatewasted","label":0},{"text":"happy to say i go way back with this birthday girl. we even pose the same way... ballers","label":2},{"text":"ha ha ha my top would be all ers pics and one beyonce niners saloonsquad","label":2},{"text":"zayn s album officially comes out on friday","label":1},{"text":"when your on a plane and don t want to eat airplane food user los angeles","label":2},{"text":"the worst sec of your life thanks for the training steve at","label":2},{"text":"enjoying the rainy day with my high school buddies! gerry s grill artesia","label":0},{"text":"merry axemas hatchi hating on this scarf actually it was a wine bottle cozy whitedogproblems","label":2},{"text":"richardbutler singing his heart out pfursofficial love you guys! the observatory orange","label":0},{"text":"braids by me on my friend user summerstyle braidstyles cornrows lahair","label":1},{"text":"i getting paid! at user in camarillo, ca","label":0},{"text":"anaheim, california","label":0},{"text":"get to see this guy in a little over a week sizerfreddie losangeles to switzerland user","label":1},{"text":"long lines mean good food. tacos overload in grand central market. la nomnom","label":0},{"text":"a word that pretty much sums up my trip so far... food","label":2},{"text":"im cryin rn","label":2},{"text":"fun with props and shooting our red mosser glass cakestand the holidays","label":0},{"text":"rocky got gorgeous today in grooming! look at that faaaaaaace lexidoginthepearl","label":1},{"text":"w my mickey babyjacob coachella, california","label":0},{"text":"user everyone got paid today shit","label":2},{"text":"my new wall mural rocks! hard to focus . you need any custom work, hit up user","label":2},{"text":"hot, angry baby! yucaipa regional lagoon amp park","label":2},{"text":"come tees cosmic slop, duppy conquerer jeans now user thanks cometees, thingsrosemakes...nn s","label":0},{"text":"a lost love note nbosken found in the caf at powell s books. powell s books, inc.","label":0},{"text":"soul brook cali is gonna pretend he ordered this and post it on ig. but i m beating him to it.","label":2},{"text":"happy birthday user .... aye this the first nigga i ever seen beat up a dog while everybody else took off we go way back bruh","label":2},{"text":"snapchat user if it s coo los angeles, california","label":2},{"text":"i have dreamt of luscious green forests for weeks. i wa. user","label":0},{"text":"pre cookies that name from inspiredextracts keep up the great work guys! sundayfunday","label":2},{"text":"awe moment of the day ottersofinstagram toocuteforwords port san luis beach","label":1},{"text":"found the local library richmond branch library user in san francisco, ca","label":0},{"text":"ermahgerd. bestsmoreever smoregram user i ve been stalking you on instagram and","label":1},{"text":"views from the gym nofilter gym beautiful marina sunshine marina del ray, marina del","label":1},{"text":"my biggest supporters since day one literally festival of","label":0},{"text":"this was a wonderful weekend with a beautiful person. venteux","label":0},{"text":"it s like a wake up and play kind of love los angeles, california","label":0},{"text":"family fun day soho soho house west hollywood","label":0},{"text":"early in the morning training at user those holidays food got me out of shape! coach","label":2},{"text":"merry christmas eve lake elsinore, california","label":0},{"text":"this guy. my . downtown container park","label":0},{"text":"user happy dance because we don t fly out until this evening disneyland","label":2},{"text":"werk that camera, frankie face servingface puppy cute cutepuppy furbaby bearface","label":1},{"text":"st bieber fever experience. thank you, justin, for putting on an amazing show for us..best","label":0},{"text":"love these girls glad we could have this trip before all of us start a new chapter of our","label":0},{"text":"lego!!! downtown disney district","label":1},{"text":"r c initials jkbyrhirtyone jewelry anniversary lucky love gem state gymnastics","label":0},{"text":"what s left my ......!!!!! lol modesto, california","label":0},{"text":"user by user for fantastics hairandmakeupbyme m.a.s.h. set malibu creek","label":0},{"text":"happy birthday to this lady at user in seattle, wa w user","label":0},{"text":"that sad moment in life when you miss getting a pic of a lady stealing sugar packets user busted","label":2},{"text":"shoshone falls shoshone falls","label":1},{"text":"fred s tavern lamb owens","label":1},{"text":"user thank you!!!","label":0},{"text":"meet amy, master masseuse with the most radiant smile! coffeelovers aharoncoffee","label":0},{"text":"they do what they want! textfromlastnight imsleep oaklandbelike itbelikethat comedy","label":2},{"text":"happynewyear losangeles irs taxes newyear downey, downey, california","label":2},{"text":"flg grooves from user woooohooow user exchange la","label":1},{"text":"shaheen love s vintage shaheen alfredshaheen hawaiian simply vintage boutique","label":0},{"text":"fly away denim springfield bootie these are legit the comfiest pair of black pants i own","label":1},{"text":"bye california... see you next week sawyer camp trail, crystal spring reservoir","label":2},{"text":"lazoonights i met icarly los angeles zoo","label":2},{"text":"gotta stop handin the spotlight to wierdo niggas","label":2},{"text":"squad out for bieber justin beiber staples center","label":1},{"text":"summa dat mornin fuckery! bakersfield, california","label":2},{"text":"as if you need any other reason to sf. are you ready marina? barrysbootcamp barryssf","label":0},{"text":"rainy day blues lovethisweather rainylosangeles northhollywoodlife lunchtime noahs ark","label":1},{"text":"huge thanks to everyone who made it out the other night! we u. hatdamn the lexington","label":0},{"text":"so thisjusthappened. angelenos them some prius picoftheday north hollywood toyota","label":0},{"text":"i ll stop the world and melt with you... missyou art artsy neonart pink neon neonlights","label":0},{"text":"prado academy gi, i loved this pradoacademy pradoacademydixon pradoacademyfairfield","label":1},{"text":"ok ok ok im done lmao dont unfollow me im done christmasclapback stayblessed trol user","label":2},{"text":"beautiful! who doesn t need more of this in their lives! oregon oregonnw thatpnwlife","label":1},{"text":"another perfect day with my perfect man devperry","label":0},{"text":"i want to wish my lil lady bug allona a happy rd birthday! getting so big so fast","label":0},{"text":"that time i got my nails did by user venus allure salon and spa","label":1},{"text":"th row from the front my babe user hooked it up for the birthday michael","label":0},{"text":"also got to go to the top of the space needle!! space needle","label":0},{"text":"exhausted safari wild animal park","label":2},{"text":"i have my own personal spartan spartanrace spartansprint ocr victory castaic lake","label":1},{"text":"love my crazy family! theyarethebest family mifamilia selfies selfiesandshit sisters","label":0},{"text":"kurt cobain amp his moonman hard rock hotel and casino las vegas","label":1},{"text":"so alive. user i can watch him dj forever. wild jingleball user","label":0},{"text":"i m so excited that i delivered this beautiful beautiful wedding to this couple this week! user","label":0},{"text":"literally can t wait for this beastcomeback rdfullalbum b uty","label":1},{"text":"brotherly california pizza kitchen","label":0},{"text":"lol this is hilarious already! midget wrestling the playhouse bar","label":2},{"text":"rodeo nights redbluffroundup red bluff fair grounds","label":0},{"text":"all my favorites rolled into one canvas taylorbos venice beach","label":1},{"text":"sb backstage pepsihalftime super bowl","label":0},{"text":"pismo beach with my two loves! nothing better that a cali road trip with family pismo","label":0},{"text":"see beyond the physical...pure heart amp soul! tiphanyadams lifecoach goldsgymvenice","label":0},{"text":"san francisco won my heart! union square, san francisco","label":0},{"text":"trusouljatv presents momma got mo sauce trusouljatv song by user los","label":2},{"text":"alessiacaraopeningact bea love her songs rose bowl stadium","label":1},{"text":"my life! mamasboy sofitel luxury hotels redwood shores","label":0},{"text":"laughed my face off! comedy store, sunset blvd","label":2},{"text":"i m so happy for my amazing friends denzel chisolm and user they were going off in","label":0},{"text":"starving at user in san francisco, ca","label":2},{"text":"beautiful. goodwork hq","label":0},{"text":"loving this soft glam makeupbyrachellegames user lait concentre user","label":1},{"text":"luxor temptations pool","label":0},{"text":"this is one heck of a life we are lucky enough to live. newport beach, california","label":0},{"text":"happy new year tropicana las vegas","label":0},{"text":"family. los angeles, california","label":0},{"text":"i media with the chainsmokers!!! drai s beach club nightclub","label":0},{"text":"shenanigans rookie what are my hands doing?!? lol reporterlife user","label":2},{"text":"it s a small world disneyland park","label":0},{"text":"maybe i ll know by the end of the day neverbeenthisoldbefore user","label":2},{"text":"dressed up as our bitmoji and recreating them didntworktho oceana high","label":2},{"text":"feelin myself in venice last night w user thanks for all the love. on to the next","label":0},{"text":"user lmao that s how i pictured it tbh","label":2},{"text":"tonight s charity event at balboa park sandiego balboapark dress backless san diego hall","label":0},{"text":"wow! wasted beauty amp the genius behind this incredible short film! wastedbeautyfilm director","label":0},{"text":"user this ones for u took me all day to him down! mickey s toontown","label":0},{"text":"a amp m s beautiful ceremony setup at omnilacosta by designerdana.lee congratulations to the","label":1},{"text":"but what fills my heart most is the special time we share with familia and friends! merry","label":0},{"text":"happy saturday dance losangeles lalife hollywood model blonde nohoarts blueeyes","label":0},{"text":"morning rain in la sunset gower studios","label":0},{"text":"and now we cover each other in cake finale to the cake . number at user avalon","label":2},{"text":"this just happened!!! congrats sister and jordan javis canton aka home!","label":0},{"text":"we re engaged disney california adventure","label":0},{"text":"cathedral city, california","label":0},{"text":"minions from despicable me at universal studios hollywood","label":2},{"text":"good morning, san francisco. duboce park","label":1},{"text":"i can not get enough of bb . sorry, r ... starwars theforceawakens d expo anaheim","label":2},{"text":"hermosa forma sea world parks san diego","label":0},{"text":"this. is. a. condom. sooooo..... shop the netflix amp chill condom link in bio! giftgoals","label":2},{"text":"this nigga is an idiot","label":2},{"text":"last stop melting to the ethereal groves of whitehorse hum music amp sound design","label":1},{"text":"the cousins are together again! travis air force base, california","label":1},{"text":"these two famphotosesh ashleesneck improv russian river brewing company","label":0},{"text":"date night with this hottie! datenightwithmylove michellerex sitka and spruce","label":1},{"text":"educationnnnnnnn children amoeba music","label":2},{"text":"tfw self love and positivity changes you more than self doubt and negativity ever could user","label":0},{"text":"when you out hiking, but all you wanna do is dance mammoth lake","label":2},{"text":"oui the nightclub girls! ouijaentertainment lanightlife soundnightclub dancers instagood","label":0},{"text":"i forgot to talk about how great thanksgiving was. thank you to family. walnut valley,","label":0},{"text":"i want a riding partner to come down here with santa monica pier","label":0},{"text":"little s first jrpga match of the year! golf ringer","label":0},{"text":"user user lol okay i will? nice come back","label":2},{"text":"zoodles in an asian bowl?! you got me, user groween. delightfully spicy sweet","label":1},{"text":"so happy i get to spend the weekend with this pretty lady. san diego state university","label":0},{"text":"when someone asks me how many clothes i have..... tag your fashion friend los angeles,","label":2},{"text":"brunch this morning with the first man to have my heart and my wonderful little sissy family","label":0},{"text":"summer foundation favorites lauramercier amorepacific becca nars makeup palette obsessed","label":1},{"text":"my year old nieces amp my year old nephew tonight! proudtia","label":0},{"text":"yesssss goldengirls drag with my mom and sis! sf victoriatheatre victoria theatre","label":2},{"text":"user a great pic or what?? ahh how i love travelling......","label":2},{"text":"man this f bass is toooo clean! if i was rich i would have of them! amp shop bass exchange","label":2},{"text":"oh, stumptown. why does anyone else even try? stumptown coffee roasters","label":0},{"text":"sooooo this happened today. universalstudioscalifornia user ilovehim","label":1},{"text":"much love, lady. mt user off home! ty nhs all your amazing care frm drs, anesthetists, nurses, hcas","label":0},{"text":"this is so funny! at vocal lesson messing up but i made a joke of it mistake error bad","label":2},{"text":"love spending time with our husband ! aria resort amp casino","label":0},{"text":"ross weeks new sandiegobaby sandiegobabyphotography sandiegobabyphotographer","label":0},{"text":"that smile user futurenowtour sleep train amphitheatre","label":1},{"text":"chefking express is too happy that alabama is winning! rolltide players sports grill","label":2},{"text":"angels are magical spirits of love. another shot from my art project with user for her","label":0},{"text":"local latte after an early am flight is key. latte berkeley townie townie restaurant,","label":0},{"text":"always a meaningful conversation with this one. user nofilter lolinda","label":0},{"text":"last week user class with user thank you for class!!i loove this","label":0},{"text":"i can say with certainty that this is the happiest i ve ever been","label":0},{"text":"life goals in plant form. san francisco, california","label":0},{"text":"how awesome is this removable skirt train from morileeofficial style dress is available","label":1},{"text":"new! user joggers hands down comfiest joggers i ve ever owned, you either gotta get","label":1},{"text":"hello old friend lol chico chicoca downtown chico, california","label":2},{"text":"from time to time my heart feels like it is going to explode, but not to worry, it s all from","label":0},{"text":"eating good! living it up! lookinggood mendocino hotel","label":1},{"text":"my grandma and grandpa! they were the best second set of parents a gal could ever ask for.","label":0},{"text":"friendsmas dinner with these crazy people. friends christmas bringon adventures","label":0},{"text":"st roadtrip oregon rowena crest, historic columbia river highway","label":1},{"text":"loving my new star wars poster!!! starwarstheforceawakens starwars nerd lightsaber disney","label":1},{"text":"to navigate wonders and finally answer to yes!!! drama grove of anaheim","label":0},{"text":"shorty gotta a lil bounce back los angeles, california","label":2},{"text":"i hate twitter sometimes clutchmore a relationship like this","label":1},{"text":"waiting for drag race royalty! dragrace redline dtla raven pandoraboxx jessicawild","label":1},{"text":"mingnmom....forever motherdaughtergang idoitallforher mingnmom motherhood niftynine user","label":0},{"text":"it s been that type of week rum i will cleanse mid month user","label":2},{"text":"narcisorodriguezparfums perfume hotel maya doubletree by hilton","label":1},{"text":"i think user might have puked in her chaser but it s still cute though eagle s pub","label":0},{"text":"my irish babes fbf tgif hozier seattle, washington","label":0},{"text":"my front door is decorated for the holidays icy silver blue winterdecorations winter","label":0},{"text":"auntie u !! happy th birthday to my beautiful great niece","label":0},{"text":"new love ...tootsie is like what .... puppy pugglelove melting .... this is karma... our","label":0},{"text":"repost in case you weren t one of the k people who saw this. i that this ochousewife","label":0},{"text":"enough said i love cali hickory brisket bison burger foodie","label":1},{"text":"you could say i m def enjoying las vegas caesars palace","label":0},{"text":"if you really want it, you won t ever stop fighting for it werfit","label":0},{"text":"good morning! it s nice to have friends! mondaymorning smile little feet","label":0},{"text":"i love this beatitul place urban light at lacma in los angeles, ca","label":0},{"text":"if she s not sleeping, nobody s sleeping fingerhooktothemouth kellenandkenzie carlsbad,","label":2},{"text":"that fog though ... golden gate bridge","label":0},{"text":"so proud of david for getting chosen as one of variety s directors to watch. parker palm","label":0},{"text":"user or that....","label":2},{"text":"degrees and sunny! sundayfunday topdownweather toplessinmyconvertible i chinohills","label":0},{"text":"rd year going to december nights and we got a free picture. datenigt balboa park","label":0},{"text":"user it s amazon baby!","label":2},{"text":"first stop, devils food cakes voodoo doughnut","label":2},{"text":"f.i.l.a riseup downtown long beach","label":0},{"text":"repost oanhsters lighter locks for summer thanks to user hairbycarolchristine","label":1},{"text":"looking at malibu sunset mb malibu manhattan beach strand","label":1},{"text":"pretty positive they love me for that finisher!!! pureformpft pftfamily pftstrong tracyca","label":2},{"text":"somebody s birthday g old club crissy field","label":0},{"text":"finally put makeup on, it s been so long!! loving how it came out. follow me on snapchat to see how","label":1},{"text":"my love coronado shores","label":1},{"text":"those harmonies mindblown harvest sunday nights","label":1},{"text":"user same same","label":2},{"text":"hope your all having a great summer so far! soakcity for me today working on a few new","label":0},{"text":"inside of our chests resides a heart that beats for our soul. our soul pushes us to make the","label":0},{"text":"day my squad! love all these people! they are so funny and crazy! love you guys! youfieweek","label":0},{"text":"today i was way too heated moreday","label":2},{"text":"s antiquarianbooks hardcover with embossed detail and gilded lettering. p.s. how is","label":1},{"text":"adidas employee store in portland, or","label":1},{"text":"ready for the show! come see my s art galleries east tonight starts at pm red","label":0},{"text":"nothing makes my heart happier than this little cutie. dog puggle love","label":0},{"text":"welcome !!! urbanart urbanwalls urbanwallsbrazil weed hollywood hollywoodsign","label":2},{"text":"family funday ...... maverickhelicopters vegas lasvegas grandcanyon firsttime","label":0},{"text":"user user you want a stones jersey? . think bigger lad","label":2},{"text":"user why did the chicken cross the road?","label":2},{"text":"celebrated my aunt s thbirthday today with family and friends!","label":1},{"text":"chocolate peppermint cookies mavenstreats chocolatepeppermint chocolatepeppermintcookies","label":1},{"text":"we may have had to tie the d glasses on... theforceawakens starwars glassesproblems user","label":2},{"text":"romance user user user house of blues san diego","label":1},{"text":"it s a death match out there... seattle, washington","label":2},{"text":"user sent me a thank you gift for bringing him to justinbieber at staples the best.","label":2},{"text":"happy janmashtami lord krishna birthday this is a very special day and those of you","label":0},{"text":"oh how i missed you these past days!!!!! neededmesomecoffee hugo s engineering co. inc","label":2},{"text":"when go on a sushi double date and your wife orders chicken nuggets. love her! thedayteam","label":0},{"text":"just landed in la and i m already eating in n out l.a.x international airport","label":0},{"text":"what the world needs now is the love of jesus westwood village old la","label":0},{"text":"when in v town! murillo s mexican food","label":0},{"text":"fbf to my dream come true sobeautifulialmostcried hogwarts wandready","label":1},{"text":"got to shoot for a bike company today with dlabarba downtown los angeles","label":1},{"text":"we may be infamous but we pretend like we are famous careysisters artist mysister","label":0},{"text":"the crossfitgames tennis stadium floor is out of control crossfit crossfitgames stubhub","label":2},{"text":"bye bye princess aurora! see you again very soon... atwater, california","label":0},{"text":"i sonoma county. travelling traveller travel california sanfrancisco sonoma wine winery","label":0},{"text":"on a shoot today in california! yay for sweaterdress weather and redlips vscocam iphone","label":0},{"text":"when your the real reason theyre doing the mannequinchallenge tb yearsago oakland,","label":2},{"text":"shrimp on shrimp on shrimp! seafood solofoods madeforchefs wilmington, california","label":1},{"text":"user i swear i couldn t either so i said imma stick with what i normally go with ps clan it is lol.","label":2},{"text":"toast to my haters yo los angeles, california","label":2},{"text":"here s to your future baby brother.. congratulations on your","label":0},{"text":"are you guys a couple? ...well, you are looking at an almost year friendship.","label":0},{"text":"didney day disneyland","label":0},{"text":"love you with my whole heart user ! dutch bros. coffee east vegas","label":1},{"text":"sushi date night! if your ever in northern california , swing by sushi sams for some amazing","label":1},{"text":"todd haynes interview wrapped amp i made a new friend sally part troll doll, part gremlin user","label":0},{"text":"family beach house night, complete with a gelato run! twans user","label":0},{"text":"missing them so much today disneyland","label":0},{"text":"user dreadsbykristopherdreww hairbykristopherdreww i love this boy so much","label":0},{"text":"another film shot i took last month in los feliz ! i shooting film los feliz, los angeles","label":0},{"text":"glad to know i can always count on user to support my personal development by ing my foursquare check ins at the gym.","label":0},{"text":"me mami y yo... bailando enriqueiglesias. te amo mucho todavia fullerton, california","label":0},{"text":"homemade scooter mount huntington beach, california","label":2},{"text":"don for the fourth. thanks boyfrand corona del mar newport","label":1},{"text":"tbt just chillin at the beach with my boy b daddysboy back in","label":0},{"text":"all set! user glamcityrocker at user tonight! be quick or be dead","label":0},{"text":"so happy i finally got to meet the beautiful dose.of.farrah the other weekend at ecc","label":1},{"text":"rain looks good on you, pasadena! pasadena, california","label":0},{"text":"if at first you don t succeed, skydiving is not for you. skydive oregon","label":2},{"text":"me and my silly little boy, theo troyternier hi dada!!! morgan hill, california","label":0},{"text":"oh cali you steal my heart i belong here. graciasmadre gracias madre","label":0},{"text":"may your holidays be filled with warmth and celebration aquafuzion","label":0},{"text":"for dinner hash house a go go user in san diego, ca","label":1},{"text":"blessed love amp greetings to all. give thanks for life regardless. . dancehallmacarena","label":0},{"text":"nice picture of reevewill with sista ana supporting the user reevefoundation","label":0},{"text":"love that my school has dog therapy day before finals destress uc santa barbara","label":0},{"text":"cannataro s restaurant","label":0},{"text":"kitty la center, washington","label":0},{"text":"murdered this burger! thanks bonezmalone for the commentary oh its good! snapchat food","label":2},{"text":"happy birthday to my best friend and companion. i love u kt dempsey s sports bar amp grill lbc","label":0},{"text":"this counts as cardio skate express","label":2},{"text":"when you re finally good on halo ! halo guardians tookamonth kills finallyfirstplace","label":2},{"text":"so proud of you two!! killin it nbcdays more days fun with user and user","label":0},{"text":"playing tourist goldengatebridge sanfrancisco marincounty igerssf marinheadlands norcal","label":0},{"text":"take me back here solvang, california","label":1},{"text":"comida!! blu jam cafe","label":0},{"text":"in my mind chilling in my car like","label":2},{"text":"today was a good day. this is seconds before i smashed her with snow timberline","label":0},{"text":"family time is the best time!! lostoros chatsworth mexicanfood papanicks happyhour los","label":1},{"text":"you go glen coco! nojunk soycandles glencoco heavenlyscent lamade user","label":2},{"text":"palasjewellery valentino johnathanadler parkerpalmsprings parker palm springs","label":0},{"text":"love, love, love superbowlmetavivor sb gratitudeoverload and more than a win","label":0},{"text":"my baby s too funny foundthisonmysnapchat home sweet home","label":2},{"text":"when you re trying to make a point but your native language gets on the way lol","label":2},{"text":"cowboy saturdaygoals goawayimsleeping snugglyblanket gettingsomegoodsleep bigandfurry","label":0},{"text":"i see you venice venice canal historic district","label":1},{"text":"baby kalei sounds like her cousin makes those same sounds keahi","label":1},{"text":"i won an articulating goofy figure for answering trivia in traditions class! agoofwinsagoof","label":0},{"text":"here is a little bts from yesterday s photoshoot where i almost froze my hands and feet solid","label":2},{"text":"all hail queen brit brit planet hollywood resort amp casino","label":1},{"text":"tbt salute to our sister sundycarter . stopping thru and giving us a rundown of her up and","label":0},{"text":"andrea played love yourself like times in the car today but i wasn t complaining","label":2},{"text":"i dont know how to dog sf lafayette california tbt san francisco, california","label":2},{"text":"our bro amp sis got married! francepartyoftwo the mitten building","label":0},{"text":"user wax paper","label":1},{"text":"whoever said diamonds are a girls best friend has never owned a dog goldenretriever","label":0},{"text":"spring please noe valley, san francisco","label":1},{"text":"me mom have you been drinking ? mom no , hell no i gotta headache she lyinn","label":2},{"text":"roadtrip livingthedream highway","label":1},{"text":"i this stadium! sdinhd sdpadres petco park","label":0},{"text":"thank you for the birthday hike! awesome views and company. sketch the most loving boxer i","label":0},{"text":"my sings! thank you, deckersadowski piotrsbca for a memory that i","label":0},{"text":"happy to see my nephews after years... familyfirst torrance, california","label":1},{"text":"first barrymore world selfie swag sexy istanbul interesting london paris turkey","label":0},{"text":"i guess that s why you don t force feed people","label":2},{"text":"last sunset of temecula valley wine country","label":0},{"text":"mommy s date today my big and cool it bff! otay ranch town center","label":0},{"text":"happy birthday to my wifey ! any old grape can become a raisin, but it takes an exceptional","label":1},{"text":"user loveeee youuuuuuuuu","label":0},{"text":"i love, love. you learn more about love and how to love every single day, i sure am.","label":0},{"text":"up to you to make today count. lead by example, don t be ratchet thursday teamwork the","label":2},{"text":"congrats to scotts valley elite j sportsmanship award winner and thank you acsanjose","label":0},{"text":"rainy days call for sharing pasta and wine with someone you sottola sotto","label":0},{"text":"thanks for the paleofoundation paleojone paleo paleosf paleopaloalto modernpaleo","label":0},{"text":"leo, too many memories leo carrillo state park","label":1},{"text":"todalavida clin clin clin clin tijuana international airport","label":2},{"text":"my two little but not so little bros fun filled day today user","label":0},{"text":"my little singer songwriter. seems right at home with a guitar in her hands. love this girl!","label":1},{"text":"my dates for the day user .cdotbdot. family universal studios hollywood","label":1},{"text":"that look though.. meetmeattheabbey menoftheabbey gaybar abbeysummer the abbey food amp","label":1},{"text":"the bald and the beautiful w user user great seeing you this weekend maz","label":2},{"text":"emy is having a blast vincent didn t want to get off!! union","label":2},{"text":"sunday funday! pumpkin carving with friends user user jennifer arredondo","label":0},{"text":"successful night! love you brats hue northbeach berkeley kids in sf gous hue sf","label":2},{"text":"seattle, washington","label":0},{"text":"who says boner?! twirly girls pole fitness","label":2},{"text":"i m like dude, listen to me and he s like wut? . hahahaha. oakwood toluca hills","label":2},{"text":"sorry mom, we re never coming home santa monica pier","label":1},{"text":"snapchatshit while waiting for tommy lama to perform makemelaugh l.a. comedy club","label":2},{"text":"haha but we hates it !!! sundayfunday grind cardio havetoputinwork gym gymhumor","label":2},{"text":"someone came to visittttt stephmakowskiart los angeles, california","label":0},{"text":"andrebfunny... going dumb in the sanctuary... comedy comedyshow comedian toptags top.tags","label":2},{"text":"the strip lasvegas springbreak the venetian las vegas","label":1},{"text":"i went to the river ... lazyriver at mgm lol gotit selfie pooldays bandana reflector","label":2},{"text":"almost to los angeles","label":1},{"text":"this shits funny af. throatgame halls lol lmao funnyshit funny haha lmfao addme","label":2},{"text":"user bottle logic brewing","label":1},{"text":"hahaha. throwback to when i was a potato throwback potatome universalstudios losangeles","label":2},{"text":"and then it hits you. you ll be married in just about a week. taking this time to reflect on","label":0},{"text":"i just walked out in shorts an ugg boots. real cali like oh hey denver how y all feelin","label":2},{"text":"breakfast user with my birthday boy starbucks","label":0},{"text":"amazing night out with the boys!! mickey s","label":1},{"text":"they all have amazing voices andprettydreads thegreen hawaiianreggae loveeeethem","label":1},{"text":"bottle tree to keep all the bad spirits away highland park","label":0},{"text":"i think i m in love! ikindawantapuppy butnotyet canyon lake,","label":0},{"text":"my brother in law cracks my up rancho deliverance shooting range","label":2},{"text":"a throwbackthursday to july long weekend in seattle. my new pal was a little tough to find user","label":2},{"text":"i can only be what i want to be back at it again with the roomie insta covers. i love singing","label":0},{"text":"good memories coachella flashback ferriswheel palmtrees sunset cloudporn memories","label":0},{"text":"what a sight to see from my apartment! university of california, irvine","label":1},{"text":"just love me nothing gets my blood pumping and adrenaline flowing like an audition. grateful","label":0},{"text":"i left my ..... sanfrancisco sftony goldengatebridge solongfornow golden gate bridge","label":0},{"text":"had an amazing time with my mama. what a sincerely wonderful woman. missing you already user","label":0},{"text":"user knows the way to a buzzingbees user pillows amp some swanky scotch scotch,","label":0},{"text":"this kid! daddysgirl van nuys golf course","label":0},{"text":"dca disney towmater matersjunkyardjamboree besties soblessedicant disney california","label":2},{"text":"mansion trailer absurd insane loveit! watch all eps user don t miss the","label":2},{"text":"holy moly grandslam baby denny s","label":1},{"text":"macadamia nuts crispy onions strings the beach the poke shack","label":1},{"text":"evening snack lunch! frozenyogurt busymonth northstarvillage northstar california resort","label":2},{"text":"loved spending the past week with these beautiful amp talented ladies!","label":0},{"text":"last oct, at a wedding with my brother and sister in law cantstopwontstop lake oswego, oregon","label":2},{"text":"check me out at djmattm soundcloud edmdropsofficial edmdrops deephouse ultra edmlifestyle","label":0},{"text":"mount rainier today free entry the whole week to celebrate national park week and the","label":0},{"text":"it s so pretty macallans public house","label":1},{"text":"loved this picture from local lifestyle magazine ship to shore cowichanbay seaside boats","label":0},{"text":"best friends for years alki beach, sw seattle","label":1},{"text":"my brother, my brother where ever he goes i go truestory insidejoke pittsburghkids","label":2},{"text":"tonight was a good night at the laugh factory laugh factory las vegas","label":2},{"text":"my mcm . baby aris loves his daddy. user arisjamestrue babyboy teacollection","label":0},{"text":"merry christmas ulit! the americana at brand","label":2},{"text":"go the fuck off the novo dtla","label":2},{"text":"love this view ericajoj yosemite tunnelview halfdome love tunnel view","label":0},{"text":"blooming tea koreatown yellow house cafe","label":0},{"text":"happy birthday th birthday to this handsome man! he finally mastered the hip pop pose! i","label":2},{"text":"same principle, right? .. totem countdown countdownnye insomniac raves rave plur nos","label":2},{"text":"still in a turkey coma but this old episode brought some laughs and hurt my belly . work it off","label":2},{"text":"our annual picture with santa i can t wait to take many more with","label":0},{"text":"yum, yum can someone make me lemon squares? miramar, san diego","label":1},{"text":"little gems. bestia dtla","label":0},{"text":"i dont think i could ever get tired of looking at you cal poly rose garden","label":1},{"text":"the key to success is having a bentley in your garage djkhaledvoice sunset boulevard,","label":2},{"text":"a little grace with a lot of grit gracedbygrit holidayparty fashionshow workwife","label":0},{"text":"finally figured out how to load this glen helen mx track","label":2},{"text":"golden hour in a special place like this the resort at pelican hill","label":1},{"text":"time for my annual eye exam! does this make me ineligible to be an nhl ref? another perfect","label":2},{"text":"one bike to rule them all. my season race whip. iamspecialized sworks","label":1},{"text":"hollywood walk of fame","label":0},{"text":"yes! user it is for our chris!so happy and proud! ucberkeley university","label":0},{"text":"thanksgiving with the west coast fayyazes san francisco, california","label":0},{"text":"tbt my babies. they ve grown so quickly. love my kids. san pedro, california","label":0},{"text":"lovely sifts at user oblation papers and press","label":0},{"text":"can you see this amazing mandap? if not, it s because it s clear! anishabaj shakordecor","label":1},{"text":"brand new wateravenuecoffee user available on our website or in our cafe. water avenue","label":1},{"text":"celebrity cruises solstice","label":2},{"text":"landon, jenny amp grandma! waffle barn","label":1},{"text":"my babies home sweet home","label":0},{"text":"purposetour los angeles, california","label":0},{"text":"california academy of sciences","label":0},{"text":"all those who wander aren t lost styled by herstyling user mua emiliimarie","label":0},{"text":"totally worth the hour wait in this spot paintthenight disneyland disneylandresort","label":1},{"text":"this is my nephew and today he s teaching a lesson on how to booty pop long beach, california","label":2},{"text":"just a reminder, doing real estate but i will definitely keep my nightlife tweets coming your way , i ll always be a bartender heart","label":0},{"text":"i knew it minney has a thing for goofy she is such a flirt....","label":2},{"text":"love my niece... sacramento, california","label":0},{"text":"do you the basic course? come get a button from vice chair joshua westwick at the basic course","label":0},{"text":"birthday dinner! they gave her a birthday centerpiece. la piazza ristorante italiano","label":0},{"text":"look at this cute little lb kettle bell! hour fitness san jose, ca","label":2},{"text":"brother time makes my happy!! civilwar gobeaves football autzen stadium","label":0},{"text":"with my lovely cousins! de leon s humble abode","label":1},{"text":"good morning with abdulaziz at sofitel los angeles at beverly hills pic","label":0},{"text":"when you you work with some baddies and y all randomly coordinate on a friday . bnks","label":1},{"text":"trying this standing desk thing today because i was told sitting is the new smoking","label":2},{"text":"wow kaylee is the best","label":0},{"text":"geary courtyard apartments","label":1},{"text":"strolling with user edmonds waterfront","label":1},{"text":"my day just got a lot better! herlikenoother screendoor restaurant","label":0},{"text":"blessed to wake up to this amazing view this morning! minivacay getaway paloverdes socal","label":0},{"text":"gracias universo por hacerme fan. the wizarding world of harry","label":0},{"text":"shoutout to vincent south hill nails for slaying my mani pedi. if you re looking for quality","label":1},{"text":"the user factory in canoga park, ca","label":0},{"text":"breakfast with my evangeline. giada vegas","label":0},{"text":"these cuties thou! thanksgivingday huskypups","label":1},{"text":"user user user wait how","label":2},{"text":"user user user user user i can t wait","label":1},{"text":"last movie before i go back finally moana w priscilyn amp jedidiah at pacific theatres glendale","label":2},{"text":"family over everything reunited balanzaclan ilovemyfamily user","label":0},{"text":"going through all the bubbles trying to find an open one bear","label":2},{"text":"haven t seen the famous brew kitty just yet, but this puppy is here! user user","label":2},{"text":"i m so excited because my daddy is home. i my dad so much. daddysgirl bestdadever perris c.a","label":0},{"text":"repost user with repostapp date night with my boo user excited to see our","label":0},{"text":"the most amazing crew, beautiful people loving their lives ourtribe itsallforlove","label":0},{"text":"haha, he s gettin it! dancing brother friends hiphop fettywap lit vibes","label":2},{"text":"toofastheisin already seattle, washington","label":2},{"text":"sunset cardiff state beach in cardiff by the sea, ca","label":0},{"text":"matcha latte with red bean milk tea lab","label":1},{"text":"damn ppl got nochill for charlie when you and your crew mess with the same women. charliesheen","label":2},{"text":"really thankful for everything up to this point especially for this miracle of mine","label":0},{"text":"love my girls nights with nikkidhayes and user girls san diego, california","label":0},{"text":"tranquil moments lemolo lake camping ground","label":1},{"text":"spent a little park time with the fam bam. the boys had a blast playing tag with their dad. user","label":0},{"text":"iris amp b. gerald cantor center for visual arts","label":1},{"text":"seen the whisper hq whisper hq in santa monica, ca","label":0},{"text":"heart hips size large only . losangeles california only . shop sale","label":0},{"text":"meeting my mother . user namm anaheim convention center","label":0},{"text":"balboa park in san diego is full of intricate craftsmanship architecture craftmanship","label":1},{"text":"french toast buttermilkinc williejanerestaurant brunch willie jane","label":0},{"text":"beautiful gardens at the bellagio veldkampstakevegas bellagio gardens","label":0},{"text":"christmas dinner in oakland sequoyah country club","label":0},{"text":"movie night out with user movies girltime trianglesquare costamesa love","label":0},{"text":"just a reminder flygirl dope selflove chefameera confidence bank of america center","label":0},{"text":"i love this man with all my heart yearanniversary the venetian las","label":0},{"text":"stay internally beautiful. be the light the world needs doyourpqrt darkveildynastyinc","label":0},{"text":"ms crosby!! gaysf gaydj circuitparty circuit folsom","label":0},{"text":"have i ever mentioned how much i hate shopping? it s just make up people!! all for my","label":2},{"text":"look at these beauties! always something new amp interesting when you wander around the nursery.","label":1},{"text":"friday dinner! yumm! bagatellela fridaynight dinnertime friendstime champagneparty","label":1},{"text":"my cousins familyisforever delta diamond farm event center","label":0},{"text":"oh man how did i get so lucky! loml sap center","label":0},{"text":"add some vintage s sunglasses to a modern day birkin hermes the dina collection","label":1},{"text":"remnants from last nights photoshoot. user tonguepop silver lake, los angeles","label":0},{"text":"the bro is back fullerton hills","label":0},{"text":"love my hawaiians we all from hawaii das why. warner pacific","label":0},{"text":"happiness anniversary mike amp vale dias disneyland","label":0},{"text":"seattle you inspire me... seattle spaceneedle art love fashion photographer passion user","label":1},{"text":"missed my best friend spokane, washington","label":1},{"text":"to san francisco portland international airport","label":0},{"text":"yesterday s glam and photography by the a team, user and user","label":0},{"text":"just want to put this out there tags by hashmeapp lol humor friendship yogapractice","label":2},{"text":"marble heaven kelly wearstler flagship","label":1},{"text":"happy birthday to one of my favorite people ever ghilyfreis love you so much !","label":0},{"text":"user user lmao not even gonna lie that was a good one","label":2},{"text":"time to get faded up mesha s gifted hands in las vegas, nv","label":0},{"text":"ain t no place like the bay sf superbowl thecity pier","label":0},{"text":"amctwd thewalkingdead the walking dead","label":1},{"text":"meet my new ride b tchezzzzz mission viejo, california","label":2},{"text":"when you can t stop laughing mid skydive. no surprise, photo by steve","label":2},{"text":"name each operative system in the photo and find one that still hasn t shipped... android","label":2},{"text":"merry christmas from my family to yours viscaya","label":0},{"text":"he doesn t even know, i m his biggest fan bothell high school","label":1},{"text":"user i loved it, then realized other people didn t, and then eventually learned it s ok to have my own unpopular opinion so .","label":0},{"text":"having a great time meeting some babes at citychiconline culver city thanks everyone for","label":1},{"text":"such a cute building downtown san diego","label":0},{"text":"makeupbyme for the grand opening of blow n glow wakeupandmakeup vegasnay","label":0},{"text":"what a week, what a team, what a party. awsreplay productionclub linq parking lot","label":0},{"text":"until one has loved an animal, a part of one s soul remains unawakened. anatole france","label":0},{"text":"wendy s place cafe","label":0},{"text":"user is saying how is during a mosh pit!! he motivated fans to do better during the","label":2},{"text":"user im gonna laugh my ass off when we knock the skins out of the playoffs again! proud of this team! gohawks","label":2},{"text":"i go extra goofy sometimes doitlikemechallenge trial pt. pershing square","label":2},{"text":"the wonderfull world or color disney dianeycaliforniaadventure worldofcolor fountains","label":1},{"text":"people are out of control! redcup starbucks crayons goodlaughs palm desert, california","label":2},{"text":"happy birthday momma super good dinner at the flying pig. the food was incredible. flying","label":0},{"text":"birthday glam with my love roro manman thank you korykurlz for slaying my hair once","label":0},{"text":"petrack park","label":0},{"text":"the local instagram community minna gallery","label":0},{"text":"i knw how to treat my hur better lfl fff beverly hills, california","label":2},{"text":"partytime!!! happy galentines day!!! user bring your gals to sip and","label":0},{"text":"aboutlastnight user thanks for having me!! user joeymartinez djmadonna you","label":1},{"text":"from italy to los angeles just for you user hollywood walk of fame","label":0},{"text":"bermudo monterey fisherman s wharf monterey, california","label":0},{"text":"ha! i came all the way to la to see guys get out of their cars to throw roll around in the street. they musta been lovers not fighters.","label":2},{"text":"the only place i know where a sampler option in the menu ends up being bigger than my face","label":2},{"text":"emma is our new favorite person. bj s restaurant and brewhouse","label":0},{"text":"cinthyahuertaaa lmfao wtf did i just watch","label":2},{"text":"prayers at towards my brother user you ll be good bro, i promise","label":0},{"text":"home. bayarea san francisco bay area","label":0},{"text":"first shipment of boxes packed with l ve and ready to go out tomorrow morning!!! thank you to","label":0},{"text":"great way to spend the weekend with loved ones santa clarita, california","label":0},{"text":"hiking is good for the soul, especially with these views griffith park trails","label":1},{"text":"last nights little snow did so much to this truck petro sparks, nv","label":2},{"text":"got to spend the day at my favorite place in the world disneyland","label":0},{"text":"thx user for a fab blowout! i ur awesome fidi salon for pampering hair beauty","label":0},{"text":"i love this man more than life!!! happywifey butterflies soinlove sokol blosser winery","label":0},{"text":"so bummed... mexicansbelike funny lol jonsanchezismyhomeboy sanchezink tattoo tattoos","label":2},{"text":"fun night with my handsome date at the user party interiordesign decor design","label":0},{"text":"whatchu looking at j k ive more days and my life will be exposed.... find out who i m","label":2},{"text":"it was so nice to have both my parents here for a month gonna miss them now that they ve both","label":1},{"text":"later brother!!!! best of luck medschool hurryupdecember","label":0},{"text":"b day at user in elk grove, ca","label":0},{"text":"look who we spotted wearing famous cosabella pajamas ! kim knows what is luxury! come experience","label":1},{"text":"i have a great boss. the picnic house","label":0},{"text":"did a dark violet red glaze on my client a few days ago. soooo pretty and shiny","label":1},{"text":"land of my exes","label":2},{"text":"womancrushwednesday i m missing allywalrath and user so","label":1},{"text":"i wonder what is going on? collegefootball sportsbook the mirage hotel and casino","label":2},{"text":"disney california adventure park","label":0},{"text":"she s mine. love this girl poulsbo, washington","label":1},{"text":"i came all the way to oregon just to see this loop. it s unique and beautiful. rowena","label":0},{"text":"user i wrote you a cute note on tadd s board","label":0},{"text":"rest in peace david canary such a kind person. it was such an honor to work with you. burbank,","label":0},{"text":"entah ini ronde ke brp with dueday, l viz, and others at asia buffet pic","label":2},{"text":"tell me what you think in the comment below... new things are coming!!! necklace","label":1},{"text":"imma be honest , i only got the drink for the cup got one from","label":2},{"text":"looking for some rad work? follow collectivetattooparlor they open up shop in september!!!","label":1},{"text":"petulaclark dogsofinstagram highland park, los angeles","label":0},{"text":"amanda siobhan! daughter los angeles, california","label":0},{"text":"the first ornament to go on the tree just had to be a weasley! iwannabeaweasley jk.rowling","label":0},{"text":"user reunited and it feelssogood mama shelter los angeles","label":1},{"text":"ahhhhhhhh ... tonight s view altitude sky lounge","label":1},{"text":"diplo photo bombing at its finest!! idk that chick on the left! me n my love","label":2},{"text":"missin my high school friends","label":0},{"text":"who did we think we were lol vegasdays tbt stbday girlstrip las vegas strip","label":1},{"text":"user i got you boo, i got you","label":0},{"text":"user would ve posted a screenshot or video of it but...social media isn t the xboxone s strongest suit.","label":2},{"text":"today s shenanigans.... . life is good. malibu pier","label":1},{"text":"lets go explore. mt.hood you are on my list! exploreoregon dreaming mt. hood, oregon","label":1},{"text":"easy money cupertino, california","label":2},{"text":"part ellizasdisneyadventure bellringers disney california adventure","label":0},{"text":"morning cuddles with toulouse??!!! yes please!!! ilovehimsomuch suchacutie","label":0},{"text":"davenport christmas tree elegance!! graysonswperry the davenport hotel","label":0},{"text":"this kook ocean beach, san francisco","label":0},{"text":"i love smoking weed w dijohn, he is hilarious.","label":2},{"text":"when user sang infinity best triple ho show ever! sap","label":0},{"text":"user come visit as soon as we move in","label":1},{"text":"happy souldoutmonday from my souldoutbaby lauseiveratrained up to honor god whole","label":0},{"text":"sincerelyvonn legit a k game","label":2},{"text":"giving back! american red cross donation center","label":2},{"text":"savoring the last days at my beautiful university senioryearnostalgia lmuclassof user","label":0},{"text":"you make the saturday crowds worthwhile. hubs disneyland","label":0},{"text":"at user magic mountain in valencia, ca","label":1},{"text":"gm thenext user los angeles, california","label":2},{"text":"disney on ice citizens business bank arena","label":0},{"text":"about the th time i ve seen coheedandcambria and they finally played my favorite song. user","label":0},{"text":"i just randomly balled up some guys right now with a quick game of basketball, i love how surprised they are when i play","label":2},{"text":"absolutely in love with my new passport holder spoils victoriasecrets passportholder","label":1},{"text":"jcole killed it coleworld the light vegas","label":0},{"text":"cooler than ever newshoes nike richnigga richgirl greyshoes swag fashionofinstagram","label":1},{"text":"free pass giveaway like to enter to win a free pass! sunday feb lbflea winners","label":0},{"text":"rest easy, pretty girl. thank you for loving us and letting us love you the falls event center","label":0},{"text":"lp cute co workers while wrong at halloween day! dogpatch","label":0},{"text":"got to have an amazing run with heyyy p such good jiu jiu to be with such good energy and","label":1},{"text":"post dole whip enchanted tiki room","label":2},{"text":"morning cuddles. santa monica, california","label":0},{"text":"gorg day ideal beach bar cowells","label":1},{"text":"okay redding shasta dam","label":1},{"text":"explorecalifornia stoneypoint nikon stoney point","label":0},{"text":"love these ladies with all my agwives goingforthegold nobu malibu","label":0},{"text":"happy birthday mom thanks letting me be your gnome and thanks for","label":0},{"text":"she ain t finished yet but i m already loving this cute, sexy, little lady tattoo ink","label":0},{"text":"loving this hupehome.com bakersfield real estate group","label":1},{"text":"i ve missed you mission dolores park user in san francisco, ca","label":1},{"text":"no makeup, messy hair amp lots of . lucky. happy burger diner","label":0},{"text":"we jack ellensburg, washington","label":0},{"text":"captured this father daughter and melts my heart everything user myhubby family","label":0},{"text":"user yes ma am","label":1},{"text":"so is this the real ceasar s palace? having an incredible time in vegas with this beauty! user","label":2},{"text":"haha i was excited for our first carriage ride mission inn riverside ca","label":2},{"text":"la patrona segerstrom center for the arts","label":0},{"text":"when you see it... urban lights lacma","label":2},{"text":"saintpablotour kanyewest oracle arena and oakland alameda county coliseum","label":1},{"text":"friday hair inspiration via user los angeles, california","label":0},{"text":"private charleskelley concert on the hornblower inspiration","label":1},{"text":"coffeeaddict coffeeislife coffeeislove mountain view, california","label":2},{"text":"hot pot!!!!!! chinese hotpot meat veggie","label":1},{"text":"never gets old. i sf ggb muni sfmta prettyfluffyclouds golden gate bridge","label":0},{"text":"she is beautiful the psychic eye","label":0},{"text":"love! the mirage hotel amp casino user for cirque du soleil the beatles love in las vegas, nv","label":1},{"text":"brownie ghiacciato because thank you! iheartthecb morenovalley ie blendedcoffee","label":1},{"text":"? that s the first","label":2},{"text":"day disneycalifornia disney california adventure","label":0},{"text":"we ve got cute lil pins in the oakland shop today! temescalalley thecrocafe pingame","label":0},{"text":"them this song gowheretheloveis .... grateful aloha thankyou goodnight music","label":0},{"text":"he s ur present thanks for ur services..,","label":2},{"text":"did you know wild alaskan salmon oil is good for your heart? come get your omega s at the","label":0},{"text":"when it s f out, eat ice cream! molly moon s homemade ice cream","label":2},{"text":"i m only here for like hours but it s worth it to see you","label":0},{"text":"is it pm yet?! i m dreaming of last weekend in san diego still this was a wall at user ,","label":1},{"text":"lasvegas onlyinamerica holiday follow fun food food lasvegasstrip italien pasta","label":0},{"text":"p i m p n ain t e a s y thundervalley rcmi companyholidayparty thunder valley","label":2},{"text":"my kingdom for.... no, wouldn t take nothing for my journey now! aquatic park","label":0},{"text":"all the browns of the family. bend, oregon","label":0},{"text":"always practice cartwheels amp dance in the sandstorms. with no","label":0},{"text":"finishing up some edit work from this recent destination wedding today fun times in downtown las","label":1},{"text":"my little monkey is back from europe! missed him so much nephew","label":0},{"text":"my view right now... mom and dad s","label":0},{"text":"had fun with anika this afternoon at the macysprom event. oh to be young again ad user","label":1},{"text":"huntington beach, california","label":2},{"text":"i got into my second house to this! meconcienten spoiled","label":1},{"text":"making of a sketch idea.. seriously i need a hobby or something techno minimal whatever","label":2},{"text":"night in paris.... wait... paris las vegas hotel amp casino","label":1},{"text":"everyone needs a light skin homie inglewoodchilling gs thursdaynightfootball g s game","label":2},{"text":"spend more time doing what you love. . perfect sundayfunday with phylicia morgan.","label":0},{"text":"big sur big sur coast","label":1},{"text":"momma s little helper cascade ridge","label":1},{"text":"user and user at the billboard music awards in las vegas, nevada bbmas","label":1},{"text":"can t wait to see my best friend after a year in days portland international airport","label":0},{"text":"londonfoodiesontour karas cupcakes napa valley","label":1},{"text":"these are the best butts corgisofinstagram fresno, california","label":1},{"text":"take aways tonight i nikkita oliver and second it s getting","label":0},{"text":"it s been a great years with my brothers . congrats on you re masters degree mark! user","label":0},{"text":"because we had to be cheesy and wear matching shirts and sweaters disneyland","label":0},{"text":"i that people my er design. , s is a lot of . urban outfitters","label":0},{"text":"one that dem finally made it all the way down lol snow sledding fun yosemite national","label":2},{"text":"this video is going viral lol clovis high south gym","label":2},{"text":"user hell yea lmao i even use it at taco bell","label":2},{"text":"happy together he always makes me smile even on crappy days user","label":0},{"text":"tbt to a great day at bfd from what feels like light years ago secondstomars shoreline","label":0},{"text":"kin ya see that it s me? lol, coolkidsonly readbetweenthelines itsallintheeyes myguys","label":0},{"text":"it s a beautiful day losangeles la lastory griffith observatory","label":1},{"text":"they made me laugh part sanfrancisco fisherman s wharf, san francisco","label":2},{"text":"how i feel about friday s marley bob marley skye lol user","label":2},{"text":"fun show last night in seattle! by the end of today, i will be in denver . here s a snippet of","label":2},{"text":"my fav u.s. navy americanholiday thdayinus california sandiego military navymilitary","label":1},{"text":"perfect remedy on the day i am not feeling my . chill walk in nature with . waiting","label":0},{"text":"singers with road rage watts st","label":2},{"text":"lake tahoe","label":0},{"text":"soon my precious... soon. badger mountain looks beautiful this morning from the dentist","label":2},{"text":"when your wedding details amp dresses are so on point, that you don t even need a filter . just a","label":1},{"text":"a beautiful woman to go with a beautiful day kariz breathtaking . congrats hannahjoy amp","label":0},{"text":"beaty and the beast wifey love gjusta","label":0},{"text":"such a beautiful view of the san fernando valley oakwood toluca hills","label":1},{"text":"i said yes!!! disneyland amp disney california adventure park","label":0},{"text":"i just can t get enough of you user user user user","label":1},{"text":"christmas eve mass with the fam st. michael catholic church, poway","label":0},{"text":"beautiful day with these lovelies goldengatebridgeview","label":0},{"text":"skippin school with my bros melrose place farmers market","label":2},{"text":"user aww now ur lil bb car is even cuter","label":0},{"text":"camp redwood christian camp retreat","label":0},{"text":"hard to believe tonight s dinner is last nights leftovers!!! ruth s chris steak house","label":0},{"text":"had a very merry christmas here in anaheim the world of color shows","label":0},{"text":"wifey for lifey embarcadero","label":0},{"text":"tthere s no place else you d rather be tonight los angeles tonight hollis and davey from love","label":0},{"text":"user user three words we shared said too early onstart with forever to the point","label":0},{"text":"tomorrow is the day, i can t wait to have you with me summer creek","label":1},{"text":"user wait till andrew sees this","label":2},{"text":"john freeburgers vvlibraryreading datewithmymonkeys","label":0},{"text":"rihanna!!!!! bitchgonnahavemymoney theforum la riri antiworldtour the forum","label":1},{"text":"me tomorrow morning lol aquarium of the pacific","label":2},{"text":"the best place in the world the disneyland park amp disney s california adventures","label":1},{"text":"biba need i say more? a amp d wholesale","label":0},{"text":"love this lil boy!!! newark, newark, california","label":0},{"text":"omg!!! now that s funny!! fitnessmeme meme sofunny funnyshit funnymeme lifting","label":2},{"text":"thank you chateau for always taking such good care of me! factoryprla chateau marmont","label":0},{"text":"stepped back into time with my babe. so much fun flashback photosession beachadventure","label":0},{"text":"i always feel so welcome at my appointments. the staff at animal dermatology clinic","label":0},{"text":"i m officially my pops! the south east, san diego","label":2},{"text":"loving our time here leavenworth, washington","label":0},{"text":"looking at the weekend like... blessedisbest clinthetl pc user tenderloin,","label":1},{"text":"the food ojai hometown foodporn osteria monte grappa","label":1},{"text":"what a great snap from user we appreciate the love la carmencita","label":0},{"text":"can t find any big brother jake anywhere...better try harder lol. amoeba music","label":2},{"text":"t wod at proper! post workout reaction crossfit crossfitproper","label":2},{"text":"girlmeetsworld kca kidschoiceawards rowanwasstuckintraffic the forum","label":2},{"text":"video calls are the best","label":1},{"text":"messi. need i really say more? copaamerica lionelmessi argvbol copa centenario","label":2},{"text":"sugar honey iced tea oakland, california","label":0},{"text":"bikepark construction underway at the jeffseymourfamilycenter in elmonte!","label":1},{"text":"winter greens getting ready for tomorrow s csa share workinghandsfarmcsa whfwintercsa","label":1},{"text":"am i not wrong? instaquote someinspirationalbullshit holidays weekends temescal,","label":2},{"text":"will pay more attention to where i park when i go to the gym from now on seagull fitness","label":2},{"text":"love seeing my buddies at user in action!!! isselb isse bioionic hairnerd","label":0},{"text":"my people dominican university of california","label":0},{"text":"fbf to last night becauseican thismantho i can t say it enough and i say it every day","label":1},{"text":"friendship being passed down through the generations... disneyland","label":0},{"text":"the dramatic music in the background.. latenight santa monica, california","label":2},{"text":"dinner with my favorite people. reunited with my bestie wangthangg al s place","label":0},{"text":"latergram i el lay hollywood hills, mulholland dr","label":0},{"text":"throwback to this pic with me and my babe babe cutestcoupleaward powercouple like love","label":1},{"text":"we you, willie. happy birthday. sayhey sfgiants at amp t park","label":0},{"text":"buffalo wild wings user in seattle, wa","label":0},{"text":"user funny toptags joke top.tags epic lol crazy fun instafun witty tweegram","label":2},{"text":"my love santa ana, california","label":2},{"text":"so thankful for each amp every sister we gained today! kappaphimu whykappaphi boisestate","label":1},{"text":"nothing like catching some astrophotography when your early to shoot sunrise . huge fan of","label":1},{"text":"every day is a magical day with my beautiful user every day is a new day waiting for new","label":0},{"text":"i u cupcakes and other vegan gluten goodies made by yours truly are sold every day at","label":0},{"text":"waited too long to catch up!!! boa santa monica","label":0},{"text":"these two dave amp buster s san jose","label":0},{"text":"ahh my lovelie, there you are!! now i m a happy another cheesecake lover can t wait to dive","label":0},{"text":"drinking the diabolical mocha have a fun thursday my friends redcup starbucks","label":0},{"text":"repost a b c with repostapp user janetwisin","label":2},{"text":"looks like me on the way to school noplease koa huntingtonbeach california","label":2},{"text":"yo user you a fool!!! playing wit that bag in la.. s o user for having","label":2},{"text":"i m in a zone at tommy bahama runway show. tommybahama seattle smgmodels tommy bahama","label":2},{"text":"user it was seriously so great to hear from you too made my day x","label":0},{"text":"w a ern la city of los angeles in los angeles, ca","label":0},{"text":"the entrance to the hideaway is so awesome. love all of these hidden gems in riverside","label":0},{"text":"haha i had to post this. damn d angelo with that bullshit again","label":2},{"text":"user was so amazing at user tonight her singing plus","label":1},{"text":"home is where the heart is disneyland","label":0},{"text":"being silly while i wait for my hair appointment keepitreal dontbesoserious","label":2},{"text":"just a snack scallop ceviche, seaweed salad, poke grand central","label":1},{"text":"miiriella mag das bild voll user if i was the kosh deal from , huh?","label":1},{"text":"when kansas boys whip and nae nae... trentandkatie watchmewhipwatchmenaenae wedding","label":2},{"text":"wait for my new line of plates .... opa!!!! by enrique user user","label":2},{"text":"day of driving with an expired plastic philippine driver s license glendale, california","label":2},{"text":"check out this cool episode one of my fave podcasts.","label":2},{"text":"it s been a while at user in las vegas, nv","label":0},{"text":"celebration devvierra s big day with the kendo family! devonandsteve weddingday","label":0},{"text":"love was love. the mirage hotel and casino","label":0},{"text":"good morning world city of concord, california","label":1},{"text":"disneyd a massive thank you for my awesome welovedisney box set. so. shiny. top l r tote","label":0},{"text":"today writing, marketing consulting, and just general ass kicking bluebeard coffee","label":0},{"text":"matoma played false alarm...i was in love. matoma omniasandiego onlyreasoniwent downtown","label":0},{"text":"after a good rain...it s just a gorgeous day in la!! i la fundaysunday san monica beach","label":0},{"text":"kicking off my footy career right eurocup las vegas convention center","label":2},{"text":"today s home office arbonneopportunity long beach, washington","label":0},{"text":"my heart is so full blessed reunited user tomato street coeur d alene","label":0},{"text":"so innocent lol bail hotline bail bonds","label":2},{"text":"nothing beats this friendships lots of catching up w a whole lot of laughter. this trip","label":0},{"text":"lunch date with my dad! elfatcat grill","label":0},{"text":"mmmmm gd bro burger","label":1},{"text":"live love soccer ... photooftheday sgfootball malaysiacup futbolsport futbol","label":0},{"text":"day of the dead highland park neighborhood","label":0},{"text":"me babe, you got your blue steel look here! ross nah, not full steel. happy new year,","label":2},{"text":"ready for disney!!! disneyland","label":1},{"text":"reading material for the plane ride home i m already tearing up. it s been such a magical week","label":0},{"text":"deezee nyland disneyland","label":0},{"text":"who dis? wcw thebabe girlsweekendthrowback vegasbaby cosmochandelier gayforbae the","label":0},{"text":"so many blessings to be grateful for, my dear husband for one happy thanksgiving to","label":1},{"text":"on saturdays we are busy!....dancing! bagalife bagatellela saturdaynight saturdaylovers","label":1},{"text":"heartshaped rocks magic cardiff ca california sandiego cardiff state beach","label":1},{"text":"love my people....my not so little anymore people snow shoe christmas tree farm","label":0},{"text":"baby, baby, oh, i miss you...","label":0},{"text":"hunger games movie premiere cast of mockingjay part staples center","label":0},{"text":"legittbrady caught me taking his picture! oakland yacht club","label":2},{"text":"tinashe show closerwithskype user live .","label":0},{"text":"spotted ourselves on tv while at the game homeplate sdinhd padres petco park","label":2},{"text":"i can t . contra costa college","label":2},{"text":"hanging out with my bridesmaids today one acts more half white than her sisters, las demas","label":0},{"text":"user really don t need intel, it s too obvious. they re smitten with each other. that s amore aldub thmonthsary","label":1},{"text":"gretsch haight ashbury","label":0},{"text":"oh look it s monday wishing this one didn t live hours away, but surprise visits are the","label":1},{"text":"what . gets you. thanks for stopping by user we always get a little giddy","label":1},{"text":"congratulations to my favorite nurse besides tiff . hollywood","label":0},{"text":"cat love city of mill valley","label":0},{"text":"the park! superb huge and pretty at user pic","label":0},{"text":"view from the lighthouse point arena lighthouse","label":1},{"text":"it s that time of year again and why not give your love of your","label":0},{"text":"omg this place !! celebrating one of my best friends bday !! happy bday you fckn whore !!","label":1},{"text":"saturdays were made for iced lattes, strawberry nutella crepes, and time with you marine","label":0},{"text":"u not even in my archive of memories... u forgotten . thank you user your post","label":2},{"text":"lasvegas by night!! love it and love you user can t wait for tomorrow","label":0},{"text":"back in la los angeles international airport lax","label":1},{"text":"back together with the bestie!! arielcwu vegaschristmas christmas bellagio las vegas","label":0},{"text":"thank you ! los angeles, california","label":0},{"text":"love that we have so much natural light gilarut sandiego sandiegohairstylist","label":1},{"text":"having a very special and unforgetable night with my handsome marine xavisus gayden i am so","label":0},{"text":"this one is for you love edclv","label":0},{"text":"i love my planetdog hat. it s gone on so many adventures with me! years of service finally","label":0},{"text":"when you have won by default. top deck restaurant at club cal neva, reno","label":2},{"text":"dcr fernhill city park","label":0},{"text":"natures form of art mammoth pools","label":1},{"text":"meeting natalie for the first time.. holtville, california","label":0},{"text":"smoking out the docs office tustin, california","label":2},{"text":"family trip to the aquarium had so much fun with them!","label":0},{"text":"l ve you so much user thank you for coming and i loveddddd your gift! you truly","label":0},{"text":"new mixed metals necklace! gunmetal triangle charm on a bronze chain. love it to stand","label":0},{"text":"home is where the heart is i just wanted to take a moment amp say how grateful i truly am","label":0},{"text":"so obsessed with user in our user gown for her engagement shoot! shot by","label":0},{"text":"things going to be better from chaos to a neat, from pollution to a clear,","label":0},{"text":"beyond thankful for my best friend. you never fail to amaze me, everyday happy thanksgiving","label":0},{"text":"nickelodeon on sunset","label":0},{"text":"me and bae about to get it! aweeeeeeeeee yeaaaaaa!!! bicepsandexercise getstrong getssome","label":2},{"text":"mercy and i smiling for our christmas pic user santa monica, california","label":0},{"text":"my girl met one of her favs again this year! anaheim convention center","label":0},{"text":"soaking in the sunset with my beautiful babe happy sunday everyone! sundayvibes","label":0},{"text":"it astounds me how seriously i used to take this show lmao theoc classic s soapy","label":2},{"text":"welcome to our new family member alf vintage authenticvintage fleamarket pasadena","label":1},{"text":"christi and family loving the ceremony. what a beautiful smile christi happy wedding eric amp","label":0},{"text":"my paseo chapultepec","label":0},{"text":"i tacospretty sure i was mexican in a past life haha. jpdneats sanfrancisco sf","label":0},{"text":"montage laguna beach","label":1},{"text":"is ending and i m still in love with california bestnine cali tbt palo alto, california","label":0},{"text":"me and the mister th letter jenniferjourneys lbc hotelmaya fuego","label":0},{"text":"days with this goober are the best krb goober wecrazy","label":0},{"text":"for my family with love my queendom","label":0},{"text":"congratulations queen!! sutter graduates. me and claudia still pending lol. sacstategrad user","label":0},{"text":"feeling the joy with my baby tonight corona, california","label":1},{"text":"i get to marry my best friend tomorrow getconklined gaslamp district, downtown san diego, ca","label":0},{"text":"playlist update is now live on spotify feat. user who i fell in with last night . also","label":0},{"text":"cartoon love girl los angeles, california","label":0},{"text":"i just can t regrann app from user crieone regrann lake elsinore, california","label":2},{"text":"frozen dead mouse reaction video. friday mouse frozen tgif siberianhusky rat","label":2},{"text":"these dresses in disneyland s soundsational parade disneyland disneylandresort","label":0},{"text":"congratulations apepagoda and fennface!!! such an amazing couple and lovely wedding","label":0},{"text":"user noooo joke","label":2},{"text":"san francisco i you sanfrancisco sb super bowl city","label":0},{"text":"mis favs rodeo drive beverley hills california","label":0},{"text":"omg. christmas overload mistletoe a holiday store","label":0},{"text":"bliss is a sunday that involves a mani pedi massage combo cha spa in santa monica, ca","label":1},{"text":"laughter is the best medicine!! redondo beach, california","label":1},{"text":"hi user ! travelbuddies redrockcanyon lasvegas nevada red rock canyon national","label":2},{"text":"another unforgettable night with amazing friends shoutout to the","label":0},{"text":"these boys are so cute!!! kandle park","label":1},{"text":"caffe dolc is bae","label":0},{"text":"family smezlife makingmemories the old spaghetti factory","label":0},{"text":". i hope he wins. goleo hollywood","label":2},{"text":"be your own kind of beautiful photooftheday picoftheday happy love beauty beautiful","label":0},{"text":"another absolutely delicious creation from the kitchen of lecoqdor ! chateaulife le coq d or","label":1},{"text":"date night datenight love earls boyfriend happy dressedup earls victoria","label":0},{"text":"familylove watsonminniatureschnauser wilcox morning hike beautiful daughters weekend fun","label":0},{"text":"big mistake..... big. huge.living that pretty women life user","label":0},{"text":"anyone ever notice that broken clocks are always set to the same time? steady eddy s","label":2},{"text":"with the babes! dave amp buster s san jose","label":0},{"text":"i missed this puppy greatdane scarlett murrieta, california","label":0},{"text":"go user !! love this woman user sdinhd padres petco stadium home of the","label":0},{"text":"happy anniversary to this wonderful couple. we love our silverbride gavinolivia so","label":0},{"text":"omfg k vs live charles w te winkle middle school","label":2},{"text":"marina del rey, venice beach, ca","label":2},{"text":"its been so long the user in san diego, ca","label":0},{"text":"that look of joy always warms my heart city of pico rivera","label":1},{"text":"smith rock run today... made misery ridge my bitch...well kind of smith rock state park","label":2},{"text":"magumausagi user you look like hugh jackman! you look like wolverine i really don t think so","label":2},{"text":"oh, stone...you just get me. drinking a stone enjoy by . . unfiltered ipa at user","label":0},{"text":"after hrs walk athena is still all smiles and alfonso photo bombing the picture user","label":2},{"text":"my city pdx burnside bridge","label":0},{"text":"flashback to me in the garden of our austin town home. gay queer top selfie gayselfie","label":0},{"text":"when your homegirls dare you to show em what you ve been learning in class secretpoledancing","label":2},{"text":"taking small bites from the bread...don t want to get full before the main course! user","label":2},{"text":"have you ever watched a movie on a rooftop? thanks rooftopcinemaclubla for a lovely evening!","label":1},{"text":"hogwarts jeminicdaotravel the wizarding world of harry potter at universal studios hollywood","label":0},{"text":"slide up in her dm like selfie sup netflixandchill coolin fearthebeard vivalasvegas","label":2},{"text":"sunday morning and eggs fuego old town eatery","label":0},{"text":"whippin in the dugout ... prstg waitonit tarheelnationprstg a lincoln ave alameda","label":2},{"text":"it is simply amazing to have a love like this!!!! heartbeat mybaby loveeeeeehim loveofmylife","label":0},{"text":"if i was you, i would be happy too! it has been a great months","label":2},{"text":"this little guy really melts my heart !! lovethegrandson ownyourlife san diego, california","label":0},{"text":"check out this couple!!! belle amp perry sales are parents of , they ve been coming to","label":1},{"text":"i got her sooooo goood! she had no idea!!! user is featuring our entire story on their","label":2},{"text":"blown away by california s central coast . paso robles, california","label":1},{"text":"blessed to have moments like these. laurel canyon dog park","label":0},{"text":"sailboats on a silver sea. losangeles california santamonica palisades ilovela ocean","label":0},{"text":"day anniversary weekend!! vegas anniversary wifey vegasliving mandalay bay resort","label":0},{"text":"butterbeer latte!!! at user in henderson, nv","label":1},{"text":"best quote ever i got plenty...... positive mindful selfaware quote losangeles artist","label":2},{"text":"sometimes the bass misbehaves! highland park, los angeles","label":2},{"text":"because i love you like my own sister nanti ada rezeki shopping","label":0},{"text":"gi name is future teacher bae. love it","label":2},{"text":"cool little shop up at arrowhead lake arrowhead, california","label":0},{"text":"rooting for the lakings... istilllovecrosby at user for user vs user in los angeles, ca","label":0},{"text":"so happy to see user county of san diego waterfront park","label":1},{"text":"lineartechparty my yearsandstillcounting aboutlastnight san jose convention","label":0},{"text":"that apple store!! apple union square","label":1},{"text":"the game awards microsoft theatre user in los angeles, ca","label":1},{"text":"another amazing meal with the best tour guide that.health.chick socal eat instafood","label":0},{"text":"walked into my house to find him by my door and i nearly wet myself.. turns out he s actually","label":2},{"text":"am cycle boeing lbfitness fitfam wakeup and get moving... followme to the gym","label":0},{"text":"i dtla! arts district, los angeles","label":0},{"text":"continue the work... look to the future. focus on the youth! producerlife i my job!","label":0},{"text":"user when american literature is going down the shitter wtf does that even mean?","label":2},{"text":"i may be past prom age....but i would love to own a pair of these shoes!! check out my twitter","label":1},{"text":"vera mae and aunt lo lo auntthed seattle, washington","label":0},{"text":"m junktour brooklyn bowl las vegas","label":0},{"text":"still, what eyes saw was more beautiful roadtrip california nature nationalgeographic","label":0},{"text":"bae user hamilton family brewery","label":0},{"text":"familygoals in our matching j crew christmas pajamas baker house","label":0},{"text":"i truly love this girl! she s the reason i ve made it this far in a short amount of time and","label":0},{"text":"the cure for all that ails. chickennoodlesoup goodformysoul n. hollywood","label":0},{"text":"time to get sappy. only cause i m sober i love this guy user he s always there","label":2},{"text":"jack london square","label":0},{"text":"lil shawty wanna see me everyday tbt my krazy life","label":0},{"text":"this view dtla perch laviews lastory perch","label":1},{"text":"officially a gamma phi beta gphicsuf delta delta chapter of","label":1},{"text":"all i need in this life of sin... is me and my girlfriends lake chelan","label":0},{"text":"breakfast with my lady quality food and beverage user in los angeles, ca","label":0},{"text":"that crssd sunset though crssdfest sandiego sunset waterfront","label":1},{"text":"this two literally is under my feet at all times... lazykitchenporters chefslife puppy","label":2},{"text":"adventuring w this guy . carmelvalley carmel valley, california","label":0},{"text":"my view. right now. thanksgiving goodness with friends! happiness gourmet foodie beverly","label":0},{"text":"tbt to a post work date with the loves of my life. lulaisabelle teote","label":2},{"text":"thank you user for making me pretty for user today!!! you! beverly hills,","label":0},{"text":"liberals smdh progun a nra rkba nagr womensrights lol silver saddle ranch amp club","label":2},{"text":"s o to my wcw sade.mariee curbing the shit outta me the st we met. the grove","label":2},{"text":"sia was amazing last night on nbcthevoice likeagirl singersongwriter voicetop teamother","label":0},{"text":"michelle sandwich two of my favorite ladies. whiskey drinks sandiego dirtythirty","label":2},{"text":"not such a quality pic for a quality night washington state university","label":1},{"text":"i wish he would just dance for me runningmanchallenge runningmanfail lovehim downtown","label":2},{"text":"more fun photos! pcpa beautyandthebeast girlsdayout pcpa pacific conservatory theatre","label":0},{"text":"hello saddleback church! glad that we can worship together here after many years worship","label":0},{"text":"lax tom bradley terminal","label":0},{"text":"user haven t i been telling you","label":2},{"text":"took my beauty to see this beauty amp damn, what a sight to see","label":1},{"text":"fresno, california","label":0},{"text":"anaheim, california","label":0},{"text":"january st gainz fitfam core evolution lsf","label":2},{"text":"we music!!!we long beach!!!and we each other!!! family, longbeachsfinest, hometownheros,","label":0},{"text":"do i really have to say what i m thankful for ?","label":0},{"text":"super fun. maybe next time i could do the actual thing! lol but i think i have to fix my posture","label":2},{"text":"happy to be back with my mother! this time we ll be together i m","label":1}]